{"stats":{"minecraft:custom":{"minecraft:jump":69,"minecraft:time_since_rest":326,"minecraft:leave_game":1,"minecraft:deaths":1,"minecraft:sprint_one_cm":4044,"minecraft:play_time":1657,"minecraft:damage_taken":270,"minecraft:time_since_death":271,"minecraft:walk_one_cm":1935,"minecraft:total_world_time":1665,"minecraft:fall_one_cm":4091,"minecraft:fly_one_cm":11501},"minecraft:picked_up":{"minecraft:birch_log":3},"minecraft:used":{"minecraft:birch_planks":12},"minecraft:mined":{"minecraft:birch_log":3,"minecraft:birch_leaves":10},"minecraft:crafted":{"minecraft:birch_planks":12}},"DataVersion":4189}